{"conjugations": [{"group": "infinitive", "group_sort": 0, "sort": 0, "value": "ganguear\n"}, {"group": "gerund", "group_sort": 1, "sort": 0, "value": "gangueando\n"}, {"form": "masculine", "group": "pastparticiple/singular", "group_sort": 2, "sort": 0, "value": "gangueado\n"}, {"form": "feminine", "group": "pastparticiple/singular", "group_sort": 2, "sort": 1, "value": "gangueada\n"}, {"form": "masculine", "group": "pastparticiple/plural", "group_sort": 3, "sort": 0, "value": "gangueados\n"}, {"form": "feminine", "group": "pastparticiple/plural", "group_sort": 3, "sort": 1, "value": "gangueadas\n"}, {"form": "s1", "group": "indicative/present", "group_sort": 4, "sort": 0, "value": "gangueo\n"}, {"form": "s2", "group": "indicative/present", "group_sort": 4, "sort": 1, "value": "gangueasgangue\u00e1s (t\u00fa) -  (vos)"}, {"form": "s3", "group": "indicative/present", "group_sort": 4, "sort": 2, "value": "ganguea\n"}, {"form": "p1", "group": "indicative/present", "group_sort": 4, "sort": 3, "value": "gangueamos\n"}, {"form": "p2", "group": "indicative/present", "group_sort": 4, "sort": 4, "value": "gangue\u00e1is\n"}, {"form": "p3", "group": "indicative/present", "group_sort": 4, "sort": 5, "value": "ganguean\n"}, {"form": "s1", "group": "indicative/imperfect", "group_sort": 5, "sort": 0, "value": "gangueaba\n"}, {"form": "s2", "group": "indicative/imperfect", "group_sort": 5, "sort": 1, "value": "gangueabas\n"}, {"form": "s3", "group": "indicative/imperfect", "group_sort": 5, "sort": 2, "value": "gangueaba\n"}, {"form": "p1", "group": "indicative/imperfect", "group_sort": 5, "sort": 3, "value": "gangue\u00e1bamos\n"}, {"form": "p2", "group": "indicative/imperfect", "group_sort": 5, "sort": 4, "value": "gangueabais\n"}, {"form": "p3", "group": "indicative/imperfect", "group_sort": 5, "sort": 5, "value": "gangueaban\n"}, {"form": "s1", "group": "indicative/preterite", "group_sort": 6, "sort": 0, "value": "gangue\u00e9\n"}, {"form": "s2", "group": "indicative/preterite", "group_sort": 6, "sort": 1, "value": "gangueaste\n"}, {"form": "s3", "group": "indicative/preterite", "group_sort": 6, "sort": 2, "value": "gangue\u00f3\n"}, {"form": "p1", "group": "indicative/preterite", "group_sort": 6, "sort": 3, "value": "gangueamos\n"}, {"form": "p2", "group": "indicative/preterite", "group_sort": 6, "sort": 4, "value": "gangueasteis\n"}, {"form": "p3", "group": "indicative/preterite", "group_sort": 6, "sort": 5, "value": "ganguearon\n"}, {"form": "s1", "group": "indicative/future", "group_sort": 7, "sort": 0, "value": "ganguear\u00e9\n"}, {"form": "s2", "group": "indicative/future", "group_sort": 7, "sort": 1, "value": "ganguear\u00e1s\n"}, {"form": "s3", "group": "indicative/future", "group_sort": 7, "sort": 2, "value": "ganguear\u00e1\n"}, {"form": "p1", "group": "indicative/future", "group_sort": 7, "sort": 3, "value": "ganguearemos\n"}, {"form": "p2", "group": "indicative/future", "group_sort": 7, "sort": 4, "value": "ganguear\u00e9is\n"}, {"form": "p3", "group": "indicative/future", "group_sort": 7, "sort": 5, "value": "ganguear\u00e1n\n"}, {"form": "s1", "group": "indicative/conditional", "group_sort": 8, "sort": 0, "value": "ganguear\u00eda\n"}, {"form": "s2", "group": "indicative/conditional", "group_sort": 8, "sort": 1, "value": "ganguear\u00edas\n"}, {"form": "s3", "group": "indicative/conditional", "group_sort": 8, "sort": 2, "value": "ganguear\u00eda\n"}, {"form": "p1", "group": "indicative/conditional", "group_sort": 8, "sort": 3, "value": "ganguear\u00edamos\n"}, {"form": "p2", "group": "indicative/conditional", "group_sort": 8, "sort": 4, "value": "ganguear\u00edais\n"}, {"form": "p3", "group": "indicative/conditional", "group_sort": 8, "sort": 5, "value": "ganguear\u00edan\n"}, {"form": "s1", "group": "subjunctive/present", "group_sort": 9, "sort": 0, "value": "ganguee\n"}, {"form": "s2", "group": "subjunctive/present", "group_sort": 9, "sort": 1, "value": "gangueesgangue\u00e9s (t\u00fa) -  (vos)"}, {"form": "s3", "group": "subjunctive/present", "group_sort": 9, "sort": 2, "value": "ganguee\n"}, {"form": "p1", "group": "subjunctive/present", "group_sort": 9, "sort": 3, "value": "gangueemos\n"}, {"form": "p2", "group": "subjunctive/present", "group_sort": 9, "sort": 4, "value": "gangue\u00e9is\n"}, {"form": "p3", "group": "subjunctive/present", "group_sort": 9, "sort": 5, "value": "gangueen\n"}, {"form": "s1", "group": "subjunctive/imperfect_ra", "group_sort": 10, "sort": 0, "value": "gangueara\n"}, {"form": "s2", "group": "subjunctive/imperfect_ra", "group_sort": 10, "sort": 1, "value": "ganguearas\n"}, {"form": "s3", "group": "subjunctive/imperfect_ra", "group_sort": 10, "sort": 2, "value": "gangueara\n"}, {"form": "p1", "group": "subjunctive/imperfect_ra", "group_sort": 10, "sort": 3, "value": "gangue\u00e1ramos\n"}, {"form": "p2", "group": "subjunctive/imperfect_ra", "group_sort": 10, "sort": 4, "value": "ganguearais\n"}, {"form": "p3", "group": "subjunctive/imperfect_ra", "group_sort": 10, "sort": 5, "value": "ganguearan\n"}, {"form": "s1", "group": "subjunctive/imperfect_se", "group_sort": 11, "sort": 0, "value": "ganguease\n"}, {"form": "s2", "group": "subjunctive/imperfect_se", "group_sort": 11, "sort": 1, "value": "gangueases\n"}, {"form": "s3", "group": "subjunctive/imperfect_se", "group_sort": 11, "sort": 2, "value": "ganguease\n"}, {"form": "p1", "group": "subjunctive/imperfect_se", "group_sort": 11, "sort": 3, "value": "gangue\u00e1semos\n"}, {"form": "p2", "group": "subjunctive/imperfect_se", "group_sort": 11, "sort": 4, "value": "gangueaseis\n"}, {"form": "p3", "group": "subjunctive/imperfect_se", "group_sort": 11, "sort": 5, "value": "gangueasen\n"}, {"form": "s1", "group": "subjunctive/future", "group_sort": 12, "sort": 0, "value": "gangueare\n"}, {"form": "s2", "group": "subjunctive/future", "group_sort": 12, "sort": 1, "value": "gangueares\n"}, {"form": "s3", "group": "subjunctive/future", "group_sort": 12, "sort": 2, "value": "gangueare\n"}, {"form": "p1", "group": "subjunctive/future", "group_sort": 12, "sort": 3, "value": "gangue\u00e1remos\n"}, {"form": "p2", "group": "subjunctive/future", "group_sort": 12, "sort": 4, "value": "gangueareis\n"}, {"form": "p3", "group": "subjunctive/future", "group_sort": 12, "sort": 5, "value": "ganguearen\n"}, {"form": "s1", "group": "imperative/affirmative", "group_sort": 13, "sort": 0, "value": "\n"}, {"form": "s2", "group": "imperative/affirmative", "group_sort": 13, "sort": 1, "value": "gangueagangue\u00e1 (t\u00fa) -  (vos)"}, {"form": "s3", "group": "imperative/affirmative", "group_sort": 13, "sort": 2, "value": "ganguee\n"}, {"form": "p1", "group": "imperative/affirmative", "group_sort": 13, "sort": 3, "value": "gangueemos\n"}, {"form": "p2", "group": "imperative/affirmative", "group_sort": 13, "sort": 4, "value": "ganguead\n"}, {"form": "p3", "group": "imperative/affirmative", "group_sort": 13, "sort": 5, "value": "gangueen\n"}, {"form": "s1", "group": "imperative/negative", "group_sort": 14, "sort": 0, "value": "\n"}, {"form": "s2", "group": "imperative/negative", "group_sort": 14, "sort": 1, "value": "no ganguees\n"}, {"form": "s3", "group": "imperative/negative", "group_sort": 14, "sort": 2, "value": "no ganguee\n"}, {"form": "p1", "group": "imperative/negative", "group_sort": 14, "sort": 3, "value": "no gangueemos\n"}, {"form": "p2", "group": "imperative/negative", "group_sort": 14, "sort": 4, "value": "no gangue\u00e9is\n"}, {"form": "p3", "group": "imperative/negative", "group_sort": 14, "sort": 5, "value": "no gangueen\n"}], "definitions": ["to speak nasally"], "description": "ganguear (first-person singular present gangueo, first-person singular preterite gangue\u00e9, past participle gangueado)", "etymology": null, "page_id": 3886036, "pronunciations": [], "related": ["gangoso", "gangueo"], "synonyms": [], "url": "https://en.wiktionary.org/?curid=3886036#Spanish", "word": "ganguear"}