{"description": "emparentar (first-person singular present empariento, first-person singular preterite emparent\u00e9, past participle emparentado)", "related": [], "word": "emparentar", "definitions": ["to become related (through marriage, etc.)", "to discover relatedness"], "page_id": 1559663, "url": "https://en.wiktionary.org/?curid=1559663#Spanish", "etymology": null, "conjugations": {"subjunctive": {"imperfect_ra": ["emparentara", "emparentaras", "emparentara", "emparent\u00e1ramos", "emparentarais", "emparentaran"], "present": ["empariente", "emparientes", "empariente", "emparentemos", "emparent\u00e9is", "emparienten"], "future": ["emparentare", "emparentares", "emparentare", "emparent\u00e1remos", "emparentareis", "emparentaren"], "imperfect_se": ["emparentase", "emparentases", "emparentase", "emparent\u00e1semos", "emparentaseis", "emparentasen"]}, "imperative": {"negative": ["", "no emparientes", "no empariente", "no emparentemos", "no emparent\u00e9is", "no emparienten"], "affirmative": ["", "emparienta (t\u00fa) - emparent\u00e1 (vos)", "empariente", "emparentemos", "emparentad", "emparienten"]}, "gerund": "emparentando", "indicative": {"conditional": ["emparentar\u00eda", "emparentar\u00edas", "emparentar\u00eda", "emparentar\u00edamos", "emparentar\u00edais", "emparentar\u00edan"], "imperfect": ["emparentaba", "emparentabas", "emparentaba", "emparent\u00e1bamos", "emparentabais", "emparentaban"], "present": ["empariento", "emparientas (t\u00fa) - emparent\u00e1s (vos)", "emparienta", "emparentamos", "emparent\u00e1is", "emparientan"], "future": ["emparentar\u00e9", "emparentar\u00e1s", "emparentar\u00e1", "emparentaremos", "emparentar\u00e9is", "emparentar\u00e1n"], "preterite": ["emparent\u00e9", "emparentaste", "emparent\u00f3", "emparentamos", "emparentasteis", "emparentaron"]}, "infinitive": "emparentar", "pastparticiple": {"singular": {"masculine": "emparentado", "feminine": "emparentada"}, "plural": {"masculine": "emparentados", "feminine": "emparentadas"}}}, "synonyms": [], "pronunciations": []}