{"description": "regenerar (first-person singular present regenero, first-person singular preterite regener\u00e9, past participle regenerado)", "related": [], "word": "regenerar", "definitions": ["to regenerate"], "page_id": 408485, "url": "https://en.wiktionary.org/?curid=408485#Spanish", "etymology": null, "conjugations": {"subjunctive": {"imperfect_ra": ["regenerara", "regeneraras", "regenerara", "regener\u00e1ramos", "regenerarais", "regeneraran"], "present": ["regenere", "regeneres (t\u00fa) - regener\u00e9s (vos)", "regenere", "regeneremos", "regener\u00e9is", "regeneren"], "future": ["regenerare", "regenerares", "regenerare", "regener\u00e1remos", "regenerareis", "regeneraren"], "imperfect_se": ["regenerase", "regenerases", "regenerase", "regener\u00e1semos", "regeneraseis", "regenerasen"]}, "imperative": {"negative": ["", "no regeneres", "no regenere", "no regeneremos", "no regener\u00e9is", "no regeneren"], "affirmative": ["", "regenera (t\u00fa) - regener\u00e1 (vos)", "regenere", "regeneremos", "regenerad", "regeneren"]}, "gerund": "regenerando", "indicative": {"conditional": ["regenerar\u00eda", "regenerar\u00edas", "regenerar\u00eda", "regenerar\u00edamos", "regenerar\u00edais", "regenerar\u00edan"], "imperfect": ["regeneraba", "regenerabas", "regeneraba", "regener\u00e1bamos", "regenerabais", "regeneraban"], "present": ["regenero", "regeneras (t\u00fa) - regener\u00e1s (vos)", "regenera", "regeneramos", "regener\u00e1is", "regeneran"], "future": ["regenerar\u00e9", "regenerar\u00e1s", "regenerar\u00e1", "regeneraremos", "regenerar\u00e9is", "regenerar\u00e1n"], "preterite": ["regener\u00e9", "regeneraste", "regener\u00f3", "regeneramos", "regenerasteis", "regeneraron"]}, "infinitive": "regenerar", "pastparticiple": {"singular": {"masculine": "regenerado", "feminine": "regenerada"}, "plural": {"masculine": "regenerados", "feminine": "regeneradas"}}}, "synonyms": [], "pronunciations": []}