{"conjugations": [{"group": "infinitive/impersonal", "group_sort": 0, "sort": 0, "value": "manipular"}, {"form": "s1", "group": "infinitive/personal", "group_sort": 1, "sort": 0, "value": "manipular"}, {"form": "s2", "group": "infinitive/personal", "group_sort": 1, "sort": 1, "value": "manipulares"}, {"form": "s3", "group": "infinitive/personal", "group_sort": 1, "sort": 2, "value": "manipular"}, {"form": "p1", "group": "infinitive/personal", "group_sort": 1, "sort": 3, "value": "manipularmos"}, {"form": "p2", "group": "infinitive/personal", "group_sort": 1, "sort": 4, "value": "manipulardes"}, {"form": "p3", "group": "infinitive/personal", "group_sort": 1, "sort": 5, "value": "manipularem"}, {"group": "gerund", "group_sort": 2, "sort": 0, "value": "manipulando"}, {"form": "s", "group": "pastparticiple/masculine", "group_sort": 3, "sort": 0, "value": "manipulado"}, {"form": "p", "group": "pastparticiple/masculine", "group_sort": 3, "sort": 1, "value": "manipulados"}, {"form": "s", "group": "pastparticiple/feminine", "group_sort": 4, "sort": 0, "value": "manipulada"}, {"form": "p", "group": "pastparticiple/feminine", "group_sort": 4, "sort": 1, "value": "manipuladas"}, {"form": "s1", "group": "indicative/present", "group_sort": 5, "sort": 0, "value": "manipulo"}, {"form": "s2", "group": "indicative/present", "group_sort": 5, "sort": 1, "value": "manipulas"}, {"form": "s3", "group": "indicative/present", "group_sort": 5, "sort": 2, "value": "manipula"}, {"form": "p1", "group": "indicative/present", "group_sort": 5, "sort": 3, "value": "manipulamos"}, {"form": "p2", "group": "indicative/present", "group_sort": 5, "sort": 4, "value": "manipulais"}, {"form": "p3", "group": "indicative/present", "group_sort": 5, "sort": 5, "value": "manipulam"}, {"form": "s1", "group": "indicative/imperfect", "group_sort": 6, "sort": 0, "value": "manipulava"}, {"form": "s2", "group": "indicative/imperfect", "group_sort": 6, "sort": 1, "value": "manipulavas"}, {"form": "s3", "group": "indicative/imperfect", "group_sort": 6, "sort": 2, "value": "manipulava"}, {"form": "p1", "group": "indicative/imperfect", "group_sort": 6, "sort": 3, "value": "manipul\u00e1vamos"}, {"form": "p2", "group": "indicative/imperfect", "group_sort": 6, "sort": 4, "value": "manipul\u00e1veis"}, {"form": "p3", "group": "indicative/imperfect", "group_sort": 6, "sort": 5, "value": "manipulavam"}, {"form": "s1", "group": "indicative/preterite", "group_sort": 7, "sort": 0, "value": "manipulei"}, {"form": "s2", "group": "indicative/preterite", "group_sort": 7, "sort": 1, "value": "manipulaste"}, {"form": "s3", "group": "indicative/preterite", "group_sort": 7, "sort": 2, "value": "manipulou"}, {"form": "p1", "group": "indicative/preterite", "group_sort": 7, "sort": 3, "value": "manipulamos - manipul\u00e1mos"}, {"form": "p2", "group": "indicative/preterite", "group_sort": 7, "sort": 4, "value": "manipulastes"}, {"form": "p3", "group": "indicative/preterite", "group_sort": 7, "sort": 5, "value": "manipularam"}, {"form": "s1", "group": "indicative/pluperfect", "group_sort": 8, "sort": 0, "value": "manipulara"}, {"form": "s2", "group": "indicative/pluperfect", "group_sort": 8, "sort": 1, "value": "manipularas"}, {"form": "s3", "group": "indicative/pluperfect", "group_sort": 8, "sort": 2, "value": "manipulara"}, {"form": "p1", "group": "indicative/pluperfect", "group_sort": 8, "sort": 3, "value": "manipul\u00e1ramos"}, {"form": "p2", "group": "indicative/pluperfect", "group_sort": 8, "sort": 4, "value": "manipul\u00e1reis"}, {"form": "p3", "group": "indicative/pluperfect", "group_sort": 8, "sort": 5, "value": "manipularam"}, {"form": "s1", "group": "indicative/future", "group_sort": 9, "sort": 0, "value": "manipularei"}, {"form": "s2", "group": "indicative/future", "group_sort": 9, "sort": 1, "value": "manipular\u00e1s"}, {"form": "s3", "group": "indicative/future", "group_sort": 9, "sort": 2, "value": "manipular\u00e1"}, {"form": "p1", "group": "indicative/future", "group_sort": 9, "sort": 3, "value": "manipularemos"}, {"form": "p2", "group": "indicative/future", "group_sort": 9, "sort": 4, "value": "manipulareis"}, {"form": "p3", "group": "indicative/future", "group_sort": 9, "sort": 5, "value": "manipular\u00e3o"}, {"form": "s1", "group": "conditional", "group_sort": 10, "sort": 0, "value": "manipularia"}, {"form": "s2", "group": "conditional", "group_sort": 10, "sort": 1, "value": "manipularias"}, {"form": "s3", "group": "conditional", "group_sort": 10, "sort": 2, "value": "manipularia"}, {"form": "p1", "group": "conditional", "group_sort": 10, "sort": 3, "value": "manipular\u00edamos"}, {"form": "p2", "group": "conditional", "group_sort": 10, "sort": 4, "value": "manipular\u00edeis"}, {"form": "p3", "group": "conditional", "group_sort": 10, "sort": 5, "value": "manipulariam"}, {"form": "s1", "group": "subjunctive/present", "group_sort": 11, "sort": 0, "value": "manipule"}, {"form": "s2", "group": "subjunctive/present", "group_sort": 11, "sort": 1, "value": "manipules"}, {"form": "s3", "group": "subjunctive/present", "group_sort": 11, "sort": 2, "value": "manipule"}, {"form": "p1", "group": "subjunctive/present", "group_sort": 11, "sort": 3, "value": "manipulemos"}, {"form": "p2", "group": "subjunctive/present", "group_sort": 11, "sort": 4, "value": "manipuleis"}, {"form": "p3", "group": "subjunctive/present", "group_sort": 11, "sort": 5, "value": "manipulem"}, {"form": "s1", "group": "subjunctive/imperfect", "group_sort": 12, "sort": 0, "value": "manipulasse"}, {"form": "s2", "group": "subjunctive/imperfect", "group_sort": 12, "sort": 1, "value": "manipulasses"}, {"form": "s3", "group": "subjunctive/imperfect", "group_sort": 12, "sort": 2, "value": "manipulasse"}, {"form": "p1", "group": "subjunctive/imperfect", "group_sort": 12, "sort": 3, "value": "manipul\u00e1ssemos"}, {"form": "p2", "group": "subjunctive/imperfect", "group_sort": 12, "sort": 4, "value": "manipul\u00e1sseis"}, {"form": "p3", "group": "subjunctive/imperfect", "group_sort": 12, "sort": 5, "value": "manipulassem"}, {"form": "s1", "group": "subjunctive/preterite", "group_sort": 13, "sort": 0, "value": "manipular"}, {"form": "s2", "group": "subjunctive/preterite", "group_sort": 13, "sort": 1, "value": "manipulares"}, {"form": "s3", "group": "subjunctive/preterite", "group_sort": 13, "sort": 2, "value": "manipular"}, {"form": "p1", "group": "subjunctive/preterite", "group_sort": 13, "sort": 3, "value": "manipularmos"}, {"form": "p2", "group": "subjunctive/preterite", "group_sort": 13, "sort": 4, "value": "manipulardes"}, {"form": "p3", "group": "subjunctive/preterite", "group_sort": 13, "sort": 5, "value": "manipularem"}, {"form": "s1", "group": "imperative/affirmative", "group_sort": 14, "sort": 0, "value": "-"}, {"form": "s2", "group": "imperative/affirmative", "group_sort": 14, "sort": 1, "value": "manipula"}, {"form": "s3", "group": "imperative/affirmative", "group_sort": 14, "sort": 2, "value": "manipule"}, {"form": "p1", "group": "imperative/affirmative", "group_sort": 14, "sort": 3, "value": "manipulemos"}, {"form": "p2", "group": "imperative/affirmative", "group_sort": 14, "sort": 4, "value": "manipulai"}, {"form": "p3", "group": "imperative/affirmative", "group_sort": 14, "sort": 5, "value": "manipulem"}, {"form": "s1", "group": "imperative/negative", "group_sort": 15, "sort": 0, "value": "-"}, {"form": "s2", "group": "imperative/negative", "group_sort": 15, "sort": 1, "value": "manipules"}, {"form": "s3", "group": "imperative/negative", "group_sort": 15, "sort": 2, "value": "manipule"}, {"form": "p1", "group": "imperative/negative", "group_sort": 15, "sort": 3, "value": "manipulemos"}, {"form": "p2", "group": "imperative/negative", "group_sort": 15, "sort": 4, "value": "manipuleis"}, {"form": "p3", "group": "imperative/negative", "group_sort": 15, "sort": 5, "value": "manipulem"}], "definitions": ["to manipulate"], "description": "manipular (first-person singular present indicative manipulo, past participle manipulado)", "etymology": "From French manipuler", "page_id": 342459, "pronunciations": [], "related": ["manipulaci\u00f3n", "manipulador"], "synonyms": [], "url": "https://en.wiktionary.org/?curid=342459#Portuguese", "word": "manipular"}