{"related": [], "etymology": null, "url": "https://en.wiktionary.org/wiki/incardinar", "definitions": ["to include"], "verb": "incardinar", "synonyms": [], "description": "incardinar (first-person singular present incardino, first-person singular preterite incardin\u00e9, past participle incardinado)", "conjugations": {"imperative": {"affirmative": ["", "incardina (t\u00fa) - incardin\u00e1 (vos)", "incardine", "incardinemos", "incardinad", "incardinen"], "negative": ["", "no incardines", "no incardine", "no incardinemos", "no incardin\u00e9is", "no incardinen"]}, "infinitive": "incardinar", "indicative": {"future": ["incardinar\u00e9", "incardinar\u00e1s", "incardinar\u00e1", "incardinaremos", "incardinar\u00e9is", "incardinar\u00e1n"], "preterite": ["incardin\u00e9", "incardinaste", "incardin\u00f3", "incardinamos", "incardinasteis", "incardinaron"], "imperfect": ["incardinaba", "incardinabas", "incardinaba", "incardin\u00e1bamos", "incardinabais", "incardinaban"], "conditional": ["incardinar\u00eda", "incardinar\u00edas", "incardinar\u00eda", "incardinar\u00edamos", "incardinar\u00edais", "incardinar\u00edan"], "present": ["incardino", "incardinas (t\u00fa) - incardin\u00e1s (vos)", "incardina", "incardinamos", "incardin\u00e1is", "incardinan"]}, "pastparticiple": {"plural": {"feminine": "incardinadas", "masculine": "incardinados"}, "singular": {"feminine": "incardinada", "masculine": "incardinado"}}, "gerund": "incardinando", "subjunctive": {"imperfect_se": ["incardinase", "incardinases", "incardinase", "incardin\u00e1semos", "incardinaseis", "incardinasen"], "future": ["incardinare", "incardinares", "incardinare", "incardin\u00e1remos", "incardinareis", "incardinaren"], "imperfect_ra": ["incardinara", "incardinaras", "incardinara", "incardin\u00e1ramos", "incardinarais", "incardinaran"], "present": ["incardine", "incardines (t\u00fa) - incardin\u00e9s (vos)", "incardine", "incardinemos", "incardin\u00e9is", "incardinen"]}}, "pronunciations": []}