{"related": ["derrocadero", "derrocamiento", "derrocarse"], "etymology": null, "url": "https://en.wiktionary.org/wiki/derrocar", "definitions": ["to hurl, to throw, to cast", "to overthrow, to bring down", "to demolish, to knock down", "to weaken, to enervate"], "verb": "derrocar", "synonyms": ["abatir", "aniquilar", "demoler", "derribar", "derruir", "destruir"], "description": "derrocar (first-person singular present derroco, first-person singular preterite derroqu\u00e9, past participle derrocado)", "conjugations": {"imperative": {"affirmative": ["", "derroca (t\u00fa) - derroc\u00e1 (vos)", "derroque", "derroquemos", "derrocad", "derroquen"], "negative": ["", "no derroques", "no derroque", "no derroquemos", "no derroqu\u00e9is", "no derroquen"]}, "infinitive": "derrocar", "indicative": {"future": ["derrocar\u00e9", "derrocar\u00e1s", "derrocar\u00e1", "derrocaremos", "derrocar\u00e9is", "derrocar\u00e1n"], "preterite": ["derroqu\u00e9", "derrocaste", "derroc\u00f3", "derrocamos", "derrocasteis", "derrocaron"], "imperfect": ["derrocaba", "derrocabas", "derrocaba", "derroc\u00e1bamos", "derrocabais", "derrocaban"], "conditional": ["derrocar\u00eda", "derrocar\u00edas", "derrocar\u00eda", "derrocar\u00edamos", "derrocar\u00edais", "derrocar\u00edan"], "present": ["derroco", "derrocas (t\u00fa) - derroc\u00e1s (vos)", "derroca", "derrocamos", "derroc\u00e1is", "derrocan"]}, "pastparticiple": {"plural": {"feminine": "derrocadas", "masculine": "derrocados"}, "singular": {"feminine": "derrocada", "masculine": "derrocado"}}, "gerund": "derrocando", "subjunctive": {"imperfect_se": ["derrocase", "derrocases", "derrocase", "derroc\u00e1semos", "derrocaseis", "derrocasen"], "future": ["derrocare", "derrocares", "derrocare", "derroc\u00e1remos", "derrocareis", "derrocaren"], "imperfect_ra": ["derrocara", "derrocaras", "derrocara", "derroc\u00e1ramos", "derrocarais", "derrocaran"], "present": ["derroque", "derroques (t\u00fa) - derroqu\u00e9s (vos)", "derroque", "derroquemos", "derroqu\u00e9is", "derroquen"]}}, "pronunciations": []}