{"description": "parlamentar (first-person singular present parlamento, first-person singular preterite parlament\u00e9, past participle parlamentado)", "related": [], "word": "parlamentar", "definitions": ["to parley"], "page_id": 343647, "url": "https://en.wiktionary.org/?curid=343647#Spanish", "etymology": null, "conjugations": {"subjunctive": {"imperfect_ra": ["parlamentara", "parlamentaras", "parlamentara", "parlament\u00e1ramos", "parlamentarais", "parlamentaran"], "present": ["parlamente", "parlamentes (t\u00fa) - parlament\u00e9s (vos)", "parlamente", "parlamentemos", "parlament\u00e9is", "parlamenten"], "future": ["parlamentare", "parlamentares", "parlamentare", "parlament\u00e1remos", "parlamentareis", "parlamentaren"], "imperfect_se": ["parlamentase", "parlamentases", "parlamentase", "parlament\u00e1semos", "parlamentaseis", "parlamentasen"]}, "imperative": {"negative": ["", "no parlamentes", "no parlamente", "no parlamentemos", "no parlament\u00e9is", "no parlamenten"], "affirmative": ["", "parlamenta (t\u00fa) - parlament\u00e1 (vos)", "parlamente", "parlamentemos", "parlamentad", "parlamenten"]}, "gerund": "parlamentando", "indicative": {"conditional": ["parlamentar\u00eda", "parlamentar\u00edas", "parlamentar\u00eda", "parlamentar\u00edamos", "parlamentar\u00edais", "parlamentar\u00edan"], "imperfect": ["parlamentaba", "parlamentabas", "parlamentaba", "parlament\u00e1bamos", "parlamentabais", "parlamentaban"], "present": ["parlamento", "parlamentas (t\u00fa) - parlament\u00e1s (vos)", "parlamenta", "parlamentamos", "parlament\u00e1is", "parlamentan"], "future": ["parlamentar\u00e9", "parlamentar\u00e1s", "parlamentar\u00e1", "parlamentaremos", "parlamentar\u00e9is", "parlamentar\u00e1n"], "preterite": ["parlament\u00e9", "parlamentaste", "parlament\u00f3", "parlamentamos", "parlamentasteis", "parlamentaron"]}, "infinitive": "parlamentar", "pastparticiple": {"singular": {"masculine": "parlamentado", "feminine": "parlamentada"}, "plural": {"masculine": "parlamentados", "feminine": "parlamentadas"}}}, "synonyms": [], "pronunciations": []}