{"related": ["acci\u00f3n"], "etymology": "From the noun acci\u00f3n, from Latin actio.", "url": "https://en.wiktionary.org/wiki/accionar", "definitions": ["to put into motion; to start", "to gesticulate"], "verb": "accionar", "synonyms": [], "description": "accionar (first-person singular present acciono, first-person singular preterite accion\u00e9, past participle accionado)", "conjugations": {"imperative": {"affirmative": ["", "acciona (t\u00fa) - accion\u00e1 (vos)", "accione", "accionemos", "accionad", "accionen"], "negative": ["", "no acciones", "no accione", "no accionemos", "no accion\u00e9is", "no accionen"]}, "infinitive": "accionar", "indicative": {"future": ["accionar\u00e9", "accionar\u00e1s", "accionar\u00e1", "accionaremos", "accionar\u00e9is", "accionar\u00e1n"], "preterite": ["accion\u00e9", "accionaste", "accion\u00f3", "accionamos", "accionasteis", "accionaron"], "imperfect": ["accionaba", "accionabas", "accionaba", "accion\u00e1bamos", "accionabais", "accionaban"], "conditional": ["accionar\u00eda", "accionar\u00edas", "accionar\u00eda", "accionar\u00edamos", "accionar\u00edais", "accionar\u00edan"], "present": ["acciono", "accionas (t\u00fa) - accion\u00e1s (vos)", "acciona", "accionamos", "accion\u00e1is", "accionan"]}, "pastparticiple": {"plural": {"feminine": "accionadas", "masculine": "accionados"}, "singular": {"feminine": "accionada", "masculine": "accionado"}}, "gerund": "accionando", "subjunctive": {"imperfect_se": ["accionase", "accionases", "accionase", "accion\u00e1semos", "accionaseis", "accionasen"], "future": ["accionare", "accionares", "accionare", "accion\u00e1remos", "accionareis", "accionaren"], "imperfect_ra": ["accionara", "accionaras", "accionara", "accion\u00e1ramos", "accionarais", "accionaran"], "present": ["accione", "acciones (t\u00fa) - accion\u00e9s (vos)", "accione", "accionemos", "accion\u00e9is", "accionen"]}}, "pronunciations": []}